rotalabs_cascade/__init__.py
rotalabs_cascade/core/__init__.py
rotalabs_cascade/core/config.py
rotalabs_cascade/core/context.py
rotalabs_cascade/core/engine.py
rotalabs_cascade/core/event.py
rotalabs_cascade/evaluation/__init__.py
rotalabs_cascade/evaluation/evaluator.py
rotalabs_cascade/learning/__init__.py
rotalabs_cascade/learning/cost_analyzer.py
rotalabs_cascade/learning/pattern_extractor.py
rotalabs_cascade/learning/proposal.py
rotalabs_cascade/learning/rule_generator.py
rotalabs_cascade/optimization/__init__.py
rotalabs_cascade/optimization/optimizer.py
rotalabs_cascade/plugins/__init__.py
rotalabs_cascade/plugins/builtin.py
rotalabs_cascade-1.0.0.dist-info/METADATA
rotalabs_cascade-1.0.0.dist-info/WHEEL
rotalabs_cascade-1.0.0.dist-info/licenses/LICENSE
rotalabs_cascade-1.0.0.dist-info/RECORD
