Metadata-Version: 2.4
Name: rotalabs-cascade
Version: 1.0.0
Summary: Configuration-driven orchestration engine for multi-stage decision routing
Project-URL: Homepage, https://rotalabs.ai
Project-URL: Documentation, https://rotalabs.github.io/rotalabs-cascade/
Project-URL: Repository, https://github.com/rotalabs/rotalabs-cascade
Author-email: Subhadip Mitra <subhadip@rotalabs.ai>, Rotalabs Research <research@rotalabs.ai>
License-Expression: AGPL-3.0-or-later
License-File: LICENSE
Keywords: async,cascade,decision,orchestration,pipeline,routing,workflow
Classifier: Development Status :: 4 - Beta
Classifier: Framework :: AsyncIO
Classifier: Intended Audience :: Developers
Classifier: License :: OSI Approved :: GNU Affero General Public License v3 or later (AGPLv3+)
Classifier: Programming Language :: Python :: 3
Classifier: Programming Language :: Python :: 3.9
Classifier: Programming Language :: Python :: 3.10
Classifier: Programming Language :: Python :: 3.11
Classifier: Programming Language :: Python :: 3.12
Classifier: Topic :: Software Development :: Libraries :: Python Modules
Classifier: Typing :: Typed
Requires-Python: >=3.9
Requires-Dist: pyyaml>=6.0
Provides-Extra: all
Requires-Dist: opentelemetry-api>=1.20.0; extra == 'all'
Requires-Dist: opentelemetry-sdk>=1.20.0; extra == 'all'
Requires-Dist: structlog>=23.0.0; extra == 'all'
Provides-Extra: dev
Requires-Dist: black>=23.0; extra == 'dev'
Requires-Dist: mypy>=1.0; extra == 'dev'
Requires-Dist: pytest-asyncio>=0.21.0; extra == 'dev'
Requires-Dist: pytest-cov>=4.0; extra == 'dev'
Requires-Dist: pytest>=7.0; extra == 'dev'
Requires-Dist: ruff>=0.1.0; extra == 'dev'
Provides-Extra: observability
Requires-Dist: opentelemetry-api>=1.20.0; extra == 'observability'
Requires-Dist: opentelemetry-sdk>=1.20.0; extra == 'observability'
Provides-Extra: structlog
Requires-Dist: structlog>=23.0.0; extra == 'structlog'
